LICENSE
README.md
setup.py
streamcapture/__init__.py
streamcapture.egg-info/PKG-INFO
streamcapture.egg-info/SOURCES.txt
streamcapture.egg-info/dependency_links.txt
streamcapture.egg-info/not-zip-safe
streamcapture.egg-info/requires.txt
streamcapture.egg-info/top_level.txt
test/test_base.py
test/test_buffer_write.py
test/test_fast_open_close.py
test/test_multi_capture_to_same_buffer.py
test/test_repeating.py