Metadata-Version: 2.1
Name: streamcapture
Version: 1.2.5
Summary: Capture output streams such as sys.stdout and sys.stderr.
Home-page: https://github.com/sloisel/streamcapture
Author: Sébastien Loisel
Author-email: sloisel@gmail.com
License: MIT
Project-URL: Documentation, https://htmlpreview.github.io/?https://github.com/sloisel/streamcapture/blob/master/streamcapture.html
Project-URL: Source, https://github.com/sloisel/streamcapture
Requires-Python: >=3
License-File: LICENSE
Requires-Dist: setuptools
Provides-Extra: doc
Requires-Dist: pdoc3>=0.7; extra == "doc"
